temperature_converter_py/__init__.py
temperature_converter_py/temperature_converter_py.py
temperature_converter_py-1.0.2.dist-info/LICENSE.txt
temperature_converter_py-1.0.2.dist-info/METADATA
temperature_converter_py-1.0.2.dist-info/WHEEL
temperature_converter_py-1.0.2.dist-info/top_level.txt
temperature_converter_py-1.0.2.dist-info/RECORD
