Metadata-Version: 2.1
Name: temperature-converter-py
Version: 1.0.2
Home-page: https://github.com/BrunoASN/temperature_converter_py
Author: Bruno Nascimento
Author-email: bruno-asn@hotmail.com
License: MIT
Project-URL: Código fonte, https://github.com/BrunoASN/temperature_converter_py
Project-URL: Download, https://github.com/BrunoASN/temperature_converter_py/archive/master.zip
Keywords: conversor,temperatura
Classifier: Development Status :: 5 - Production/Stable
Classifier: Intended Audience :: Developers
Classifier: License :: OSI Approved :: MIT License
Classifier: Natural Language :: Portuguese (Brazilian)
Classifier: Operating System :: OS Independent
Classifier: Topic :: Software Development :: Internationalization
Classifier: Topic :: Scientific/Engineering :: Physics
Requires-Python: >=3.4
License-File: LICENSE.txt
